hhs_vertretungsplan_parser/__init__.py
hhs_vertretungsplan_parser/const.py
hhs_vertretungsplan_parser/vertretungsplan_parser.py
hhs_vertretungsplan_parser/model/__init__.py
hhs_vertretungsplan_parser/model/vertretung.py
hhs_vertretungsplan_parser-0.1.4.dist-info/LICENSE
hhs_vertretungsplan_parser-0.1.4.dist-info/METADATA
hhs_vertretungsplan_parser-0.1.4.dist-info/WHEEL
hhs_vertretungsplan_parser-0.1.4.dist-info/top_level.txt
hhs_vertretungsplan_parser-0.1.4.dist-info/RECORD
