Metadata-Version: 2.1
Name: hhs-vertretungsplan-parser
Version: 0.1.4
Summary: A simple parser for Heinrich-Hertz-Schule, Hamburg, class substitution schedule
Home-page: https://github.com/kongo09/hhs-vertretungsplan
Author: kongo09
Author-email: kongo09@gmail.com
License: MIT License
Project-URL: Bug Tracker, https://github.com/kongo09/hhs-vertretungsplan/issues
Keywords: hhs
Platform: UNKNOWN
Requires-Python: !=2.*,>=3.6
License-File: LICENSE
Requires-Dist: aiohttp (>=3.5.2)
Requires-Dist: beautifulsoup4 (>=4.10.0)
Requires-Dist: dateparser (>=1.1.0)
Provides-Extra: all
Requires-Dist: pytest (>=6.2.2) ; extra == 'all'
Requires-Dist: pytest-asyncio ; extra == 'all'
Requires-Dist: pytest-aiohttp ; extra == 'all'
Requires-Dist: pytest-cov ; extra == 'all'
Provides-Extra: test
Requires-Dist: pytest (>=6.2.2) ; extra == 'test'
Requires-Dist: pytest-asyncio ; extra == 'test'
Requires-Dist: pytest-aiohttp ; extra == 'test'
Requires-Dist: pytest-cov ; extra == 'test'
